README.md
setup.cfg
setup.py
msgpackrpc/__init__.py
msgpackrpc/_version.py
msgpackrpc/address.py
msgpackrpc/client.py
msgpackrpc/compat.py
msgpackrpc/error.py
msgpackrpc/future.py
msgpackrpc/loop.py
msgpackrpc/message.py
msgpackrpc/server.py
msgpackrpc/session.py
msgpackrpc/transport/__init__.py
msgpackrpc/transport/tcp.py
rpc_msgpack.egg-info/PKG-INFO
rpc_msgpack.egg-info/SOURCES.txt
rpc_msgpack.egg-info/dependency_links.txt
rpc_msgpack.egg-info/requires.txt
rpc_msgpack.egg-info/top_level.txt