Metadata-Version: 1.1
Name: rpc-msgpack
Version: 0.6
Summary: RPC with MessagePack
Home-page: UNKNOWN
Author: Eatron Technologies
Author-email: enes.toptas@eatron.com
License: UNKNOWN
Platform: UNKNOWN
Classifier: Programming Language :: Python :: 3
